easyaikit/__init__.py
easyaikit/__main__.py
easyaikit/cli.py
easyaikit/client.py
easyaikit/session.py
easyaikit/storage.py
easyaikit/utils.py
easyaikit-1.0.0.dist-info/LICENSE
easyaikit-1.0.0.dist-info/METADATA
easyaikit-1.0.0.dist-info/WHEEL
easyaikit-1.0.0.dist-info/entry_points.txt
easyaikit-1.0.0.dist-info/top_level.txt
easyaikit-1.0.0.dist-info/RECORD
